radial_map/__init__.py
radial_map/driver.py
radial_map-0.1.dist-info/METADATA
radial_map-0.1.dist-info/WHEEL
radial_map-0.1.dist-info/top_level.txt
radial_map-0.1.dist-info/RECORD
